{
	"animations": [
		{
			"loop": false,
			"offsets": [
				-3,
				5
			],
			"anim": "hey",
			"fps": 24,
			"name": "BF HEY",
			"indices": []
		},
		{
			"loop": true,
			"offsets": [
				-4,
				130
			],
			"anim": "scared",
			"fps": 24,
			"name": "BF idle shaking",
			"indices": []
		},
		{
			"offsets": [
				7,
				19
			],
			"loop": false,
			"fps": 24,
			"anim": "singLEFTmiss",
			"indices": [],
			"name": "BF LEFT MISS"
		},
		{
			"offsets": [
				-15,
				-19
			],
			"loop": false,
			"fps": 24,
			"anim": "singDOWNmiss",
			"indices": [],
			"name": "BF DOWN MISS"
		},
		{
			"offsets": [
				-46,
				27
			],
			"loop": false,
			"fps": 24,
			"anim": "singUPmiss",
			"indices": [],
			"name": "BF UP MISS"
		},
		{
			"offsets": [
				-44,
				22
			],
			"loop": false,
			"fps": 24,
			"anim": "singRIGHTmiss",
			"indices": [],
			"name": "BF RIGHT MISS"
		},
		{
			"loop": false,
			"offsets": [
				-5,
				144
			],
			"anim": "singLEFT",
			"fps": 24,
			"name": "BF NOTE LEFT0",
			"indices": []
		},
		{
			"loop": false,
			"offsets": [
				44,
				118
			],
			"anim": "singUP",
			"fps": 24,
			"name": "BF NOTE UP0",
			"indices": []
		},
		{
			"loop": false,
			"offsets": [
				-20,
				9
			],
			"anim": "singDOWN",
			"fps": 24,
			"name": "BF NOTE DOWN0",
			"indices": []
		},
		{
			"loop": false,
			"offsets": [
				32,
				103
			],
			"anim": "singRIGHT",
			"fps": 24,
			"name": "BF NOTE RIGHT0",
			"indices": []
		},
		{
			"loop": true,
			"offsets": [
				-4,
				130
			],
			"anim": "endphase2",
			"fps": 24,
			"name": "BF idle shaking",
			"indices": []
		},
		{
			"offsets": [
				-5,
				120
			],
			"indices": [],
			"fps": 24,
			"anim": "idle",
			"loop": true,
			"name": "BF idle shaking"
		}
	],
	"no_antialiasing": true,
	"image": "characters/plexitripletroublep1-og",
	"position": [
		0,
		350
	],
	"healthicon": "plexitt-og",
	"flip_x": true,
	"healthbar_colors": [
		205,
		98,
		88
	],
	"camera_position": [
		0,
		0
	],
	"sing_duration": 4,
	"scale": 1
}